tests/__init__.py
tests/benchmark.py
tests/test_algorithms.py
tests/test_causal_graphs.py
tests/test_delayed_impact.py
tests/test_dice.py
tests/test_dynamics.py
tests/test_framework.py
tests/test_opioid.py
tests/test_simulators.py
tests/test_world2.py
tests/test_world3.py
whynot/__init__.py
whynot/causal_graphs.py
whynot/dynamics.py
whynot/framework.py
whynot/utils.py
whynot/algorithms/__init__.py
whynot/algorithms/causal_suite.py
whynot/algorithms/ols.py
whynot/algorithms/propensity_score_matching.py
whynot/algorithms/propensity_weighted_ols.py
whynot/gym/__init__.py
whynot/gym/envs/__init__.py
whynot/gym/envs/ode_env.py
whynot/gym/envs/registration.py
whynot/gym/spaces/__init__.py
whynot/gym/utils/__init__.py
whynot/simulators/.DS_Store
whynot/simulators/__init__.py
whynot/simulators/civil_violence/README.md
whynot/simulators/civil_violence/__init__.py
whynot/simulators/civil_violence/experiments.py
whynot/simulators/civil_violence/model.py
whynot/simulators/civil_violence/simulator.py
whynot/simulators/credit/README.md
whynot/simulators/credit/__init__.py
whynot/simulators/credit/credit_data.zip
whynot/simulators/credit/dataloader.py
whynot/simulators/credit/environments.py
whynot/simulators/credit/simulator.py
whynot/simulators/delayed_impact/.DS_Store
whynot/simulators/delayed_impact/README.md
whynot/simulators/delayed_impact/__init__.py
whynot/simulators/delayed_impact/experiments.py
whynot/simulators/delayed_impact/fico.py
whynot/simulators/delayed_impact/simulator.py
whynot/simulators/delayed_impact/data/totals.csv
whynot/simulators/delayed_impact/data/transrisk_cdf_by_race_ssa.csv
whynot/simulators/delayed_impact/data/transrisk_performance_by_race_ssa.csv
whynot/simulators/dice/README.md
whynot/simulators/dice/__init__.py
whynot/simulators/dice/experiments.py
whynot/simulators/dice/simulator.py
whynot/simulators/dice/doc/gams_2013.txt
whynot/simulators/dice/ipopt_bin/README.md
whynot/simulators/dice/ipopt_bin/coin-license.txt
whynot-0.12.0.dist-info/LICENSE.txt
whynot-0.12.0.dist-info/METADATA
whynot-0.12.0.dist-info/WHEEL
whynot-0.12.0.dist-info/top_level.txt
whynot-0.12.0.dist-info/RECORD
