Metadata-Version: 2.1
Name: whynot
Version: 0.12.0
Summary: A framework for benchmarking causal inference.
Home-page: UNKNOWN
Author: John Miller
Author-email: miller_john@berkeley.edu
License: UNKNOWN
Platform: UNKNOWN
Classifier: Programming Language :: Python :: 3
Classifier: License :: OSI Approved :: MIT License
Classifier: Operating System :: MacOS
Classifier: Operating System :: POSIX
Requires-Python: >=3.6
Requires-Dist: autograd
Requires-Dist: gym
Requires-Dist: mesa
Requires-Dist: numpy
Requires-Dist: networkx
Requires-Dist: pandas
Requires-Dist: pyomo
Requires-Dist: py-mini-racer
Requires-Dist: scipy
Requires-Dist: sklearn
Requires-Dist: statsmodels
Requires-Dist: tqdm
Requires-Dist: dataclasses ; python_version < "3.7"
